README.md
setup.py
pruebas/__init__.py
pysbs_peru/CuponCero.py
pysbs_peru/IndiceSpreadsCorporativo.py
pysbs_peru/VectorPrecioRentaFija.py
pysbs_peru/__init__.py
pysbs_peru/common.py
pysbs_peru/settings.py
pysbs_peru.egg-info/PKG-INFO
pysbs_peru.egg-info/SOURCES.txt
pysbs_peru.egg-info/dependency_links.txt
pysbs_peru.egg-info/entry_points.txt
pysbs_peru.egg-info/requires.txt
pysbs_peru.egg-info/top_level.txt
test/__init__.py
test/test_IndiceSpreadsCorporativo.py