Metadata-Version: 2.1
Name: pysbs-peru
Version: 0.0.5
Summary: pysbs-peru Cliente Python no oficial para acceder a datos financieros públicos de la SBS Perú (Curvas, Vectores, Spreads) | Market Data Perú | Finanzas
Download-URL: https://URL_PAQUETE/pysbs-peru/-/archive/master/pysbs-peru-master.tar
Author: Erik Carl Candela Rojas
Author-email: erik.candela.rojas@gmail.com
License: NOTFOUND
Keywords: pysbs-peru,paquete,package,sbs web scraping,curva cupon cero,Vector Precio Renta Fija,Indice Spreads Corporativo
Classifier: Development Status :: 4 - Beta
Classifier: Intended Audience :: Developers
Classifier: Topic :: Software Development :: Build Tools
Classifier: Programming Language :: Python :: 3.8
Requires-Python: >=3.8
Requires-Dist: pandas>=1.5.3
Requires-Dist: numpy>=1.24.4
Requires-Dist: plotly>=5.15.0
Requires-Dist: beautifulsoup4>=4.12.3
Requires-Dist: tabula-py>=2.7.0
Requires-Dist: PyYAML
Requires-Dist: pyarrow
Requires-Dist: openpyxl>=3.0.7
Requires-Dist: pyxlsb>=1.0.9
Requires-Dist: xlrd>=2.0.1
Requires-Dist: lxml>=4.9.0
Requires-Dist: html5lib>=1.1
